{"type":"View","props":{"width":576,"name":"PanelPvpReward","height":1024},"compId":2,"child":[{"type":"Sprite","props":{"width":576,"top":0,"texture":"res/alpha_mask.png","name":"cc_mask","left":0,"height":1024},"compId":33},{"type":"Image","props":{"width":0,"name":"cc_bg","height":0,"centerY":0,"centerX":0},"compId":34,"child":[{"type":"Box","props":{"y":-512,"x":-288,"width":576,"height":1024},"compId":100,"child":[{"type":"Sprite","props":{"y":129,"x":66,"texture":"res/ui/pnl_role_test/art_04.png","name":"cc_spriteMaskBg"},"compId":101},{"type":"Sprite","props":{"y":130,"x":115,"texture":"res/ui/pnl_pvp_reward/art_01.png","name":"cc_spriteSuit"},"compId":102},{"type":"Sprite","props":{"y":95,"x":16,"texture":"res/ui/pnl_role_test/art_03.png"},"compId":103}]}]},{"type":"Box","props":{"y":0,"x":0,"width":1,"top":0,"name":"AnchorTopLeft","left":0,"height":1},"compId":97,"child":[{"type":"Sprite","props":{"name":"cc_topLeftNode"},"compId":98,"child":[{"type":"Sprite","props":{"y":160,"x":43,"width":72,"texture":"res/ui/btns/btn_back.png","pivotY":48,"pivotX":43,"name":"cc_buttonClose","height":76},"compId":99}]}]},{"type":"Box","props":{"width":1,"name":"AnchorBottom","height":1,"centerX":0,"bottom":0},"compId":105,"child":[{"type":"Image","props":{"y":-200,"x":0,"skin":"res/ui/pnl_common/pnl_bottom1.png","height":400,"bottom":1,"anchorY":0.5,"anchorX":0.5,"sizeGrid":"246,0,2,0"},"compId":106,"child":[{"type":"Image","props":{"y":160,"x":384,"width":550,"skin":"res/ui/pnl_pvp_reward/art_04.png","anchorY":0.5,"anchorX":0.5,"sizeGrid":"0,38,0,39"},"compId":107,"child":[{"type":"Label","props":{"y":8,"x":25,"wordWrap":true,"width":257,"valign":"middle","text":"区级比赛胜1场","name":"cc_labelDesc","height":56,"fontSize":18,"color":"#ffffff","align":"center"},"compId":108},{"type":"Sprite","props":{"y":79,"x":16,"texture":"res/ui/pnl_pvp_reward/art_06.png"},"compId":109,"child":[{"type":"Sprite","props":{"y":0,"x":0,"texture":"res/ui/pnl_pvp_reward/art_07.png","name":"cc_barMaskReward"},"compId":110}]},{"type":"Sprite","props":{"y":-3,"x":280,"texture":"res/ui/pnl_pvp_reward/art_03.png"},"compId":111,"child":[{"type":"Sprite","props":{"y":59,"x":59,"width":70,"texture":"res/icon/gold.png","pivotY":35,"pivotX":35,"name":"cc_spriteIconReward","height":70},"compId":120},{"type":"Box","props":{"y":95,"x":59,"width":1,"scaleY":0.65,"scaleX":0.65,"name":"cc_boxStars","height":1,"anchorY":0.5,"anchorX":0.5},"compId":121,"child":[{"type":"Script","props":{"itemSize":28,"runtime":"script/extensions/component/UIHVLayout.ts"},"compId":122},{"type":"Sprite","props":{"texture":"res/icon/star.png"},"compId":123},{"type":"Sprite","props":{"y":0,"x":0,"texture":"res/icon/star.png"},"compId":124},{"type":"Sprite","props":{"y":0,"x":0,"texture":"res/icon/star.png"},"compId":127},{"type":"Sprite","props":{"y":0,"x":0,"texture":"res/icon/star.png"},"compId":128},{"type":"Sprite","props":{"y":0,"x":0,"texture":"res/icon/star.png"},"compId":129}]}]},{"type":"Label","props":{"y":59,"x":470,"text":"未达成","name":"cc_labelState","fontSize":20,"color":"#ffffff","anchorY":0.5,"anchorX":0.5},"compId":201},{"type":"Sprite","props":{"y":59,"x":470,"texture":"res/ui/btns/btn_c03b00.png","pivotY":25,"pivotX":65,"name":"cc_buttonReceive"},"compId":95,"child":[{"type":"Label","props":{"y":15,"x":64,"width":91,"valign":"middle","text":"领取","height":18,"fontSize":20,"color":"#df5401","anchorX":0.5,"align":"center"},"compId":96,"child":[{"type":"Script","props":{"__key__":"classColorEgg.2","runtime":"script/common/I18nComponent.ts"},"compId":202}]},{"type":"Sprite","props":{"y":0,"x":105,"texture":"res/ui/btns/tip.png","name":"tip"},"compId":130}]}]},{"type":"Sprite","props":{"y":220,"x":114,"width":540,"name":"cc_scrollPart","height":180},"compId":199,"child":[{"type":"Script","props":{"itemWidth":90,"itemHeight":90,"elastic":false,"eachCount":6,"runtime":"script/extensions/component/ReuseScrollList.ts"},"compId":200}]}]}]}],"loadList":["res/alpha_mask.png","res/ui/pnl_role_test/art_04.png","res/ui/pnl_pvp_reward/art_01.png","res/ui/pnl_role_test/art_03.png","res/ui/btns/btn_back.png","res/ui/pnl_common/pnl_bottom1.png","res/ui/pnl_pvp_reward/art_04.png","res/ui/pnl_pvp_reward/art_06.png","res/ui/pnl_pvp_reward/art_07.png","res/ui/pnl_pvp_reward/art_03.png","res/icon/gold.png","res/icon/star.png","res/ui/btns/btn_c03b00.png","res/ui/btns/tip.png"],"loadList3D":[]}