{"type":"View","props":{"width":576,"name":"PanelDanceAnswer","height":1024},"compId":2,"child":[{"type":"Sprite","props":{"width":576,"top":0,"texture":"res/alpha_mask.png","name":"cc_mask","left":0,"height":1024},"compId":22},{"type":"Box","props":{"width":1,"height":1,"centerY":60,"centerX":0},"compId":53,"child":[{"type":"Sprite","props":{"y":-495,"x":-172,"texture":"res/ui/pnl_dance/art_19.png"},"compId":59},{"type":"Image","props":{"y":-415,"x":0,"width":201,"skin":"res/ui/pnl_weituo/dialog_other.png","height":113,"sizeGrid":"0,27,0,37"},"compId":55,"child":[{"type":"Box","props":{"y":4,"x":25,"width":163,"name":"cc_nodeLayoutLabel","height":104},"compId":57,"child":[{"type":"Label","props":{"y":-1,"x":1,"wordWrap":true,"width":161,"valign":"middle","text":"画在左上角有几率成功","name":"cc_labelCankao","height":107,"fontSize":18,"color":"#228fff","align":"left"},"compId":56}]}]},{"type":"Box","props":{"y":-40,"x":0,"width":1,"name":"cc_bg","height":1},"compId":23,"child":[{"type":"Image","props":{"y":-232,"x":-220,"skin":"res/ui/pnl_common/pnl_bg.png","scaleX":1,"name":"bg","height":550,"centerY":0,"sizeGrid":"189,0,139,0"},"compId":3,"child":[{"type":"Sprite","props":{"y":90,"x":80,"texture":"res/ui/pnl_common/title_bg.png","name":"titleBg","sizeGrid":"0,144,0,144"},"compId":41,"child":[{"type":"Label","props":{"y":23,"x":142,"wordWrap":true,"width":235,"valign":"middle","text":"如何跳出孔雀舞","name":"cc_titleLabel","height":45,"fontSize":15,"color":"#ffffff","anchorY":0.5,"anchorX":0.5,"align":"center"},"compId":24}]},{"type":"Image","props":{"y":145,"x":33,"skin":"res/ui/pnl_dance/art_18.png","name":"pnlInner"},"compId":43,"child":[{"type":"Sprite","props":{"y":12,"x":24,"texture":"res/ui/pnl_dance/art_05.png","scaleY":0.9,"scaleX":0.9,"name":"cc_nodeGou"},"compId":73},{"type":"Box","props":{"y":77,"x":62.5,"width":1,"name":"cc_node1","height":1},"compId":60},{"type":"Box","props":{"y":77,"x":187.5,"width":1,"name":"cc_node2","height":1},"compId":61},{"type":"Box","props":{"y":77,"x":312.5,"width":1,"name":"cc_node3","height":1},"compId":62},{"type":"Box","props":{"y":171,"x":62.5,"width":1,"name":"cc_node4","height":1},"compId":63},{"type":"Box","props":{"y":171,"x":187.5,"width":1,"name":"cc_node5","height":1},"compId":64},{"type":"Box","props":{"y":171,"x":312.5,"width":1,"name":"cc_node6","height":1},"compId":65},{"type":"Box","props":{"y":265,"x":62.5,"width":1,"name":"cc_node7","height":1},"compId":67},{"type":"Box","props":{"y":265,"x":187.5,"width":1,"name":"cc_node8","height":1},"compId":68},{"type":"Box","props":{"y":265,"x":312.5,"width":1,"name":"cc_node9","height":1},"compId":69},{"type":"Box","props":{"y":265,"x":313,"width":1,"name":"cc_nodeTips","height":1},"compId":70,"child":[{"type":"Sprite","props":{"y":-22,"x":-23,"texture":"res/ui/pnl_dance/art_23.png"},"compId":72},{"type":"Sprite","props":{"y":-50,"x":-60,"texture":"res/ui/pnl_dance/art_32.png"},"compId":71}]}]},{"type":"Sprite","props":{"y":90,"x":414,"width":48,"texture":"res/ui/btns/btn_close.png","pivotY":24,"pivotX":24,"name":"cc_buttonClose","height":48},"compId":51}]},{"type":"Sprite","props":{"y":225,"x":1,"width":201,"texture":"res/ui/btns/btn_ff840c.png","pivotY":37,"pivotX":101,"name":"cc_buttonSure","height":73},"compId":32,"child":[{"type":"Label","props":{"y":14,"x":101,"wordWrap":true,"width":134,"valign":"middle","text":"前往舞会","strokeColor":"#ff840c","stroke":2,"name":"label","height":41,"fontSize":20,"color":"#ffffff","anchorX":0.5,"align":"center"},"compId":35,"child":[{"type":"Script","props":{"__key__":"panelContract.8","runtime":"script/common/I18nComponent.ts"},"compId":75}]}]}]}]}],"loadList":["res/alpha_mask.png","res/ui/pnl_dance/art_19.png","res/ui/pnl_weituo/dialog_other.png","res/ui/pnl_common/pnl_bg.png","res/ui/pnl_common/title_bg.png","res/ui/pnl_dance/art_18.png","res/ui/pnl_dance/art_05.png","res/ui/pnl_dance/art_23.png","res/ui/pnl_dance/art_32.png","res/ui/btns/btn_close.png","res/ui/btns/btn_ff840c.png"],"loadList3D":[]}