{"type":"View","props":{"width":576,"name":"PanelClassRoleDetail","height":1024},"compId":2,"child":[{"type":"Sprite","props":{"y":0,"x":0,"width":576,"texture":"res/alpha_mask.png","name":"cc_mask","height":1024},"compId":79},{"type":"Image","props":{"skin":"res/ui/pnl_school_yearbook/art_13.png","scaleX":1,"name":"bg","centerY":-50,"centerX":0,"anchorY":0.5,"anchorX":0.5},"compId":3,"child":[{"type":"Label","props":{"y":105,"x":70,"text":"xx同学","name":"cc_labelName","fontSize":22,"color":"#d28084","anchorY":0.5,"anchorX":0},"compId":147},{"type":"Label","props":{"y":148,"x":70,"text":"暂无奖励","name":"cc_labelLevel","fontSize":22,"color":"#d28084","anchorY":0.5,"anchorX":0},"compId":181},{"type":"Label","props":{"y":192,"x":70,"text":"学校","name":"cc_labelSchool","fontSize":22,"color":"#d28084","anchorY":0.5,"anchorX":0},"compId":182},{"type":"Label","props":{"y":235,"x":70,"text":"班级","name":"cc_labelClass","fontSize":22,"color":"#d28084","anchorY":0.5,"anchorX":0},"compId":183},{"type":"Box","props":{"y":315,"x":345,"name":"cc_nodeSpine"},"compId":174},{"type":"Label","props":{"y":341,"x":70,"name":"cc_labelDesc","leading":5,"fontSize":20,"color":"#af6f71","anchorY":0,"anchorX":0},"compId":168},{"type":"Image","props":{"y":532,"x":239,"skin":"res/ui/pnl_weituo/art_01.png","name":"cc_buttonSure","anchorY":0.5,"anchorX":0.5},"compId":178,"child":[{"type":"Label","props":{"y":12,"x":61,"text":"确定","fontSize":32,"color":"#de5605"},"compId":179,"child":[{"type":"Script","props":{"__key__":"panelAdvCostDialog.2","runtime":"script/common/I18nComponent.ts"},"compId":184}]}]}]}],"loadList":["res/alpha_mask.png","res/ui/pnl_school_yearbook/art_13.png","res/ui/pnl_weituo/art_01.png"],"loadList3D":[]}