{"type":"View","props":{"width":576,"name":"PanelOverCommon","height":1024},"compId":2,"child":[{"type":"Sprite","props":{"y":0,"x":0,"width":576,"texture":"res/alpha_mask.png","name":"cc_mask","height":1024},"compId":71},{"type":"Box","props":{"width":1,"name":"cc_bg","height":1,"centerY":-160,"centerX":0},"compId":69,"child":[{"type":"Image","props":{"y":-255,"x":-244,"skin":"res/ui/pnl_common/art_01.png","name":"cc_bgImage"},"compId":3},{"type":"Image","props":{"y":-60,"x":-197,"width":390,"skin":"res/ui/pnl_common/art_02.png","name":"pnlInner","height":240,"sizeGrid":"39,35,42,39"},"compId":43},{"type":"Sprite","props":{"y":-236,"x":-230,"width":480,"pivotY":23,"pivotX":10,"name":"cc_buttonFullScreenShare","height":580},"compId":89,"child":[{"type":"Label","props":{},"compId":90}]},{"type":"Sprite","props":{"y":-7,"x":0,"name":"cc_rankNode"},"compId":78,"child":[{"type":"Sprite","props":{"y":-33,"x":-172,"texture":"res/ui/pnl_skincare/my_rank.png"},"compId":55,"child":[{"type":"Sprite","props":{"y":75,"x":0,"texture":"res/ui/pnl_skincare/line.png"},"compId":66},{"type":"Sprite","props":{"y":115,"x":0,"texture":"res/ui/pnl_skincare/line.png"},"compId":67},{"type":"Sprite","props":{"y":155,"x":0,"texture":"res/ui/pnl_skincare/line.png"},"compId":68},{"type":"Sprite","props":{"y":195,"x":0,"texture":"res/ui/pnl_skincare/line.png"},"compId":65},{"type":"Sprite","props":{"y":40,"x":2,"texture":"res/ui/pnl_skincare/rank_1.png"},"compId":58},{"type":"Sprite","props":{"y":80,"x":2,"texture":"res/ui/pnl_skincare/rank_2.png"},"compId":59},{"type":"Sprite","props":{"y":120,"x":2,"texture":"res/ui/pnl_skincare/rank_3.png"},"compId":60},{"type":"Text","props":{"y":160,"x":13,"text":"4","name":"cc_rank4","fontSize":30,"align":"center","runtime":"laya.display.Text"},"compId":61}]},{"type":"Text","props":{"y":-32,"x":-166,"wordWrap":true,"width":332,"valign":"middle","text":"我的排名：50","name":"cc_myRank","height":36,"fontSize":23,"color":"#e16e07","align":"center","runtime":"laya.display.Text"},"compId":56},{"type":"Label","props":{"y":5,"x":-38,"wordWrap":false,"width":150,"valign":"middle","text":"幻想物语","name":"cc_templateName","height":36,"fontSize":17,"color":"#229bad","anchorX":0.5,"align":"center"},"compId":62},{"type":"Label","props":{"y":6,"x":47,"wordWrap":true,"width":133,"valign":"middle","text":"积分：1130","name":"cc_templateScore","height":32,"fontSize":17,"color":"#f95b93","align":"center"},"compId":63}]},{"type":"Label","props":{"y":18,"x":-125,"wordWrap":true,"width":281,"valign":"top","text":"恭喜你给娃娃增加了60点心情","name":"cc_descLabel","leading":10,"height":116,"fontSize":22,"color":"#229bad","align":"center"},"compId":80},{"type":"Sprite","props":{"y":-115,"x":-124,"texture":"res/i18n/zhcn/pnl_skincare_01.png","name":"cc_spriteScore"},"compId":54},{"type":"Label","props":{"y":-160,"x":16,"wordWrap":true,"width":232,"valign":"middle","text":"太棒了！你真厉害！","name":"cc_titleLabel","height":38,"fontSize":15,"color":"#ffffff","anchorY":0.5,"anchorX":0.5,"align":"center"},"compId":24},{"type":"Sprite","props":{"y":-210,"x":-210,"texture":"res/icon_head/1.png","name":"cc_spriteRole"},"compId":70},{"type":"Sprite","props":{"y":-165,"x":200,"width":48,"texture":"res/ui/btns/btn_close.png","pivotY":24,"pivotX":24,"name":"cc_buttonClose","height":48},"compId":31},{"type":"Label","props":{"y":-94,"x":55,"text":"5213","name":"cc_myScore","fontSize":24,"anchorY":0.5,"anchorX":0.5},"compId":64},{"type":"Sprite","props":{"y":323,"x":-195,"width":390,"texture":"res/ui/pnl_chn/emb_bg.png","name":"cc_advNode","height":108,"centerX":1},"compId":81,"child":[{"type":"Label","props":{"y":28,"x":206,"text":"今日头条","name":"title","fontSize":20,"color":"#ffffff","anchorY":0.5,"anchorX":0.5},"compId":82},{"type":"Label","props":{"y":41,"x":104,"wordWrap":true,"width":190,"text":"文字描述文字描述文字描述文字描述文字描述文字描述文字描","name":"desc","fontSize":18,"color":"#ffffff","align":"center"},"compId":83},{"type":"Sprite","props":{"y":14,"x":15,"width":80,"name":"icon","height":80},"compId":84},{"type":"Text","props":{"y":13.5,"x":344,"text":"广告","name":"ad","fontSize":16,"color":"#ffffff","runtime":"laya.display.Text"},"compId":85},{"type":"Image","props":{"y":59,"x":335,"skin":"res/ui/pnl_chn/btn_adv.png","scaleY":0.8,"scaleX":0.8,"name":"btnClick","anchorY":0.5,"anchorX":0.5},"compId":86,"child":[{"type":"Label","props":{"y":19,"x":54,"text":"点击下载","name":"btnText","fontSize":18,"color":"#c05819","anchorY":0.5,"anchorX":0.5},"compId":87}]}]},{"type":"Sprite","props":{"name":"cc_btnNode"},"compId":88,"child":[{"type":"Sprite","props":{"y":245,"x":1,"width":201,"texture":"res/ui/btns/btn_ff61dc.png","pivotY":37,"pivotX":101,"name":"cc_buttonOk","height":73},"compId":50,"child":[{"type":"Label","props":{"y":17,"x":101,"wordWrap":true,"width":121,"valign":"middle","text":"好的","strokeColor":"#ff61dc","stroke":2,"height":36,"fontSize":20,"color":"#ffffff","anchorX":0.5,"align":"center"},"compId":52,"child":[{"type":"Script","props":{"__key__":"panelItemGet.1","runtime":"script/common/I18nComponent.ts"},"compId":91}]}]}]}]}],"loadList":["res/alpha_mask.png","res/ui/pnl_common/art_01.png","res/ui/pnl_common/art_02.png","res/ui/pnl_skincare/my_rank.png","res/ui/pnl_skincare/line.png","res/ui/pnl_skincare/rank_1.png","res/ui/pnl_skincare/rank_2.png","res/ui/pnl_skincare/rank_3.png","res/i18n/zhcn/pnl_skincare_01.png","res/icon_head/1.png","res/ui/btns/btn_close.png","res/ui/pnl_chn/emb_bg.png","res/ui/pnl_chn/btn_adv.png","res/ui/btns/btn_ff61dc.png"],"loadList3D":[]}